[
  {
    "slug": "ai-agent",
    "badge": "AI Solution",
    "title": "AI-ассистент",
    "subtitle": "Цифровой сотрудник 24/7 для ответов клиентам и автоматизации заявок",
    "timeline": "10–21 день",
    "telegramLink": "https://t.me/neeklo",
    "features": [
      "Ответы 24/7",
      "Интеграция с CRM",
      "Обучение на ваших данных",
      "Аналитика диалогов"
    ],
    "audiences": [
      { "icon": "ShoppingBag", "title": "Интернет-магазины", "description": "Ответы по товарам, статусы, возвраты" },
      { "icon": "Briefcase", "title": "Услуги", "description": "Приём заявок и напоминания" },
      { "icon": "GraduationCap", "title": "Образование", "description": "Расписание и записи" },
      { "icon": "Users", "title": "B2B", "description": "Типовые вопросы и бриф" }
    ],
    "packages": [
      {
        "id": "basic",
        "name": "Базовый",
        "description": "Быстрый старт для малого бизнеса",
        "price": "от 65 000 ₽",
        "features": [
          "1 канал: сайт или Telegram",
          "Интеграция с Google Sheets",
          "До 20 сценариев ответов",
          "Запуск — от 10 дней",
          "Поддержка 30 дней"
        ]
      },
      {
        "id": "standard",
        "name": "Стандарт",
        "description": "Для растущего бизнеса",
        "price": "от 95 000 ₽",
        "features": [
          "3 канала: сайт, Telegram, WhatsApp",
          "Интеграция с Bitrix24 / amoCRM",
          "До 50 сценариев",
          "Базовая аналитика",
          "Запуск — от 14 дней",
          "Поддержка 60 дней"
        ]
      },
      {
        "id": "premium",
        "name": "Премиум",
        "description": "Полная автоматизация",
        "price": "от 150 000 ₽",
        "features": [
          "Все каналы + голосовой бот",
          "Кастомные интеграции",
          "Неограниченные сценарии",
          "Расширенная аналитика",
          "Fine-tuning на ваших данных",
          "Запуск — от 21 дня",
          "Поддержка 90 дней"
        ]
      }
    ],
    "cases": [
      { "title": "Интернет-магазин одежды", "result": "35% заявок перешли в заказы", "metrics": ["+35% конверсия", "−40% нагрузка"] },
      { "title": "Онлайн-школа английского", "result": "AI записывает на уроки 24/7", "metrics": ["24/7 работа", "+60 записей/мес"] }
    ],
    "faq": [
      { "question": "Что такое AI-агент?", "answer": "Умный чат-бот, обученный на данных вашего бизнеса. Понимает контекст, отвечает как живой сотрудник и сохраняет данные в CRM." },
      { "question": "Как быстро будет готов?", "answer": "Базовый — 10 дней, Стандарт — 14 дней, Премиум — от 21 дня. После запуска дообучаем на реальных диалогах." },
      { "question": "Что если AI ошибётся?", "answer": "При сложных вопросах передаёт диалог оператору. Первые 2 недели мониторим ответы. Точность 95%+ после калибровки." },
      { "question": "Работает с моей CRM?", "answer": "Да — Bitrix24, amoCRM, 1C, Google Sheets, Notion и любые системы с API." }
    ]
  },
  {
    "slug": "telegram-bot",
    "badge": "Telegram",
    "title": "Telegram-бот",
    "subtitle": "Чат-бот для заявок, продаж и поддержки с интеграциями",
    "timeline": "5–14 дней",
    "telegramLink": "https://t.me/neeklo",
    "features": [
      "Приём заявок",
      "Уведомления",
      "Интеграция с CRM",
      "Оплата в боте"
    ],
    "audiences": [
      { "icon": "Store", "title": "E-commerce", "description": "Магазины и каталоги в боте" },
      { "icon": "Calendar", "title": "Услуги", "description": "Запись, напоминания, CRM" },
      { "icon": "Trophy", "title": "Геймификация", "description": "Бонусы и лояльность" },
      { "icon": "Building", "title": "Бизнес", "description": "Внутренние сервисы и B2B" }
    ],
    "packages": [
      {
        "id": "basic",
        "name": "Бот",
        "description": "Простой чат-бот для старта",
        "price": "от 35 000 ₽",
        "features": ["До 15 команд", "Форма заявки", "Уведомления", "Запуск — 5 дней", "Поддержка 14 дней"]
      },
      {
        "id": "standard",
        "name": "Бот + Интеграции",
        "description": "Бот с CRM и оплатой",
        "price": "от 65 000 ₽",
        "features": ["До 30 команд", "Интеграция с CRM", "Оплата в боте", "Рассылки", "Запуск — 10 дней", "Поддержка 30 дней"]
      },
      {
        "id": "premium",
        "name": "Mini App",
        "description": "Полноценное приложение",
        "price": "от 120 000 ₽",
        "features": ["Веб-интерфейс в Telegram", "Личный кабинет", "AI-ответы", "Геймификация", "Запуск — 14 дней", "Поддержка 60 дней"]
      }
    ],
    "cases": [
      { "title": "Салон красоты", "result": "Онлайн-запись без менеджера", "metrics": ["+200 записей/мес", "0 пропущенных"] },
      { "title": "Фитнес-клуб", "result": "Mini App с абонементами", "metrics": ["+50% продлений", "−60% звонков"] }
    ],
    "faq": [
      { "question": "Чем бот отличается от Mini App?", "answer": "Бот — это текстовый интерфейс с командами. Mini App — полноценное веб-приложение внутри Telegram с красивым UI." },
      { "question": "Работает ли в MAX?", "answer": "Да, мы разрабатываем решения для Telegram и VK/MAX мессенджеров." },
      { "question": "Можно принимать оплату?", "answer": "Да — ЮKassa, CloudPayments, Stripe и другие платёжные системы." }
    ]
  },
  {
    "slug": "mini-app",
    "badge": "Telegram",
    "title": "Mini App",
    "subtitle": "Каталог, заказ или личный кабинет прямо в Telegram",
    "timeline": "10–30 дней",
    "telegramLink": "https://t.me/neeklo",
    "features": [
      "Веб-интерфейс в Telegram",
      "Личный кабинет",
      "Оплата в приложении",
      "Push-уведомления"
    ],
    "audiences": [
      { "icon": "ShoppingCart", "title": "E-commerce", "description": "Магазин в Telegram" },
      { "icon": "Ticket", "title": "Билеты", "description": "Продажа и бронь" },
      { "icon": "Trophy", "title": "Геймификация", "description": "Бонусы и программы лояльности" },
      { "icon": "Building", "title": "Бизнес", "description": "Внутренние сервисы" }
    ],
    "packages": [
      {
        "id": "basic",
        "name": "Базовый",
        "description": "MVP приложения",
        "price": "от 80 000 ₽",
        "features": ["До 5 экранов", "Авторизация Telegram", "Базовый дизайн", "Запуск — 10 дней", "Поддержка 14 дней"]
      },
      {
        "id": "standard",
        "name": "Стандарт",
        "description": "Полное приложение",
        "price": "от 150 000 ₽",
        "features": ["До 15 экранов", "Оплата в приложении", "Личный кабинет", "Push-уведомления", "Запуск — 21 день", "Поддержка 30 дней"]
      },
      {
        "id": "premium",
        "name": "Премиум",
        "description": "Сложный продукт",
        "price": "от 300 000 ₽",
        "features": ["Неограниченные экраны", "Кастомный дизайн", "Интеграции с API", "Геймификация", "Запуск — 30 дней", "Поддержка 90 дней"]
      }
    ],
    "cases": [
      { "title": "Фитнес-клуб", "result": "Расписание и абонементы в Telegram", "metrics": ["+50% продлений", "−60% звонков"] },
      { "title": "Кофейня", "result": "Программа лояльности", "metrics": ["+30% повторных", "5000 пользователей"] }
    ],
    "faq": [
      { "question": "Чем отличается от бота?", "answer": "Mini App — полноценный интерфейс как мобильное приложение, но внутри Telegram." },
      { "question": "Работает на всех устройствах?", "answer": "Да — iOS, Android и десктоп версия Telegram." },
      { "question": "Можно интегрировать с сайтом?", "answer": "Да, Mini App может работать как часть вашей экосистемы." }
    ]
  },
  {
    "slug": "website",
    "badge": "Web",
    "title": "Сайт для бизнеса",
    "subtitle": "Лендинг, корпоративный сайт или магазин под ключ",
    "timeline": "5–14 дней",
    "telegramLink": "https://t.me/neeklo",
    "features": [
      "Готовый дизайн",
      "Адаптив под мобильные",
      "SEO-структура",
      "Админ-панель"
    ],
    "audiences": [
      { "icon": "Rocket", "title": "Стартапы", "description": "Быстрый запуск MVP" },
      { "icon": "Building", "title": "Бизнес", "description": "Корпоративные сайты" },
      { "icon": "ShoppingBag", "title": "E-commerce", "description": "Интернет-магазины" },
      { "icon": "User", "title": "Эксперты", "description": "Персональные сайты" }
    ],
    "packages": [
      {
        "id": "basic",
        "name": "Лендинг",
        "description": "Одностраничный сайт",
        "price": "от 45 000 ₽",
        "features": ["1 страница", "Адаптивный дизайн", "Форма заявки", "Базовое SEO", "Запуск — 5 дней"]
      },
      {
        "id": "standard",
        "name": "Корпоративный",
        "description": "Многостраничный сайт",
        "price": "от 120 000 ₽",
        "features": ["До 10 страниц", "Уникальный дизайн", "CMS-панель", "SEO-оптимизация", "Запуск — 14 дней", "Поддержка 30 дней"]
      },
      {
        "id": "premium",
        "name": "Магазин",
        "description": "E-commerce решение",
        "price": "от 250 000 ₽",
        "features": ["Каталог товаров", "Корзина и оплата", "Личный кабинет", "Интеграции", "Запуск — 30 дней", "Поддержка 60 дней"]
      }
    ],
    "cases": [
      { "title": "IT-компания", "result": "Корпоративный сайт за 2 недели", "metrics": ["+180% лидов", "PageSpeed 98"] },
      { "title": "Онлайн-курсы", "result": "Лендинг с высокой конверсией", "metrics": ["12% конверсия", "+300 заявок"] }
    ],
    "faq": [
      { "question": "На чём делаете сайты?", "answer": "React, Next.js, Tailwind — современный стек для быстрых и красивых сайтов." },
      { "question": "Можно редактировать самому?", "answer": "Да, подключаем удобную CMS-панель для управления контентом." },
      { "question": "Включено ли SEO?", "answer": "Да — техническая оптимизация, мета-теги, sitemap и robots.txt." }
    ]
  },
  {
    "slug": "ai-video",
    "badge": "AI Creative",
    "title": "Видео для продаж",
    "subtitle": "Reels, промо и презентации с AI — в 10 раз дешевле студии",
    "timeline": "3–7 дней",
    "telegramLink": "https://t.me/neeklo",
    "features": [
      "AI-генерация",
      "Сценарий под ЦА",
      "Озвучка и субтитры",
      "Любые форматы"
    ],
    "audiences": [
      { "icon": "Megaphone", "title": "Маркетинг", "description": "Рекламные ролики" },
      { "icon": "Instagram", "title": "SMM", "description": "Reels и Stories" },
      { "icon": "Presentation", "title": "Бизнес", "description": "Презентации" },
      { "icon": "GraduationCap", "title": "Обучение", "description": "Курсы и гайды" }
    ],
    "packages": [
      {
        "id": "basic",
        "name": "Базовый",
        "description": "3 ролика",
        "price": "от 25 000 ₽",
        "features": ["3 видео до 60 сек", "AI-генерация", "Базовый монтаж", "1 правка", "Срок — 5 дней"]
      },
      {
        "id": "standard",
        "name": "Стандарт",
        "description": "10 роликов",
        "price": "от 65 000 ₽",
        "features": ["10 видео до 60 сек", "Сценарий под ЦА", "Озвучка", "Субтитры", "Срок — 7 дней", "2 правки"]
      },
      {
        "id": "premium",
        "name": "Премиум",
        "description": "Контент-план",
        "price": "от 150 000 ₽",
        "features": ["30 видео/месяц", "Стратегия контента", "AI-аватар", "Полный продакшн", "Еженедельная доставка"]
      }
    ],
    "cases": [
      { "title": "Маркетплейс", "result": "30 карточек товаров за неделю", "metrics": ["+45% кликов", "−80% затрат"] },
      { "title": "Онлайн-школа", "result": "Reels для продвижения курса", "metrics": ["+10K подписчиков", "200K просмотров"] }
    ],
    "faq": [
      { "question": "Это выглядит как AI?", "answer": "Нет — используем premium-модели и профессиональную доработку. Результат неотличим от студийного." },
      { "question": "Можно с живым актёром?", "answer": "Да — AI-аватар или реальная съёмка с AI-обработкой." },
      { "question": "Какие форматы?", "answer": "Любые — вертикальные Reels, горизонтальные для YouTube, квадратные для постов." }
    ]
  },
  {
    "slug": "automation",
    "badge": "Automation",
    "title": "Автоматизация",
    "subtitle": "Интеграции, CRM, рассылки — меньше рутины, больше продаж",
    "timeline": "7–60 дней",
    "telegramLink": "https://t.me/neeklo",
    "features": [
      "Аудит процессов",
      "Интеграции с CRM",
      "Автоматические рассылки",
      "Обучение команды"
    ],
    "audiences": [
      { "icon": "Building", "title": "Компании", "description": "Автоматизация отделов" },
      { "icon": "ShoppingCart", "title": "E-commerce", "description": "Заказы и склад" },
      { "icon": "Users", "title": "HR", "description": "Найм и онбординг" },
      { "icon": "BarChart", "title": "Аналитика", "description": "Отчёты и дашборды" }
    ],
    "packages": [
      {
        "id": "basic",
        "name": "Базовый",
        "description": "1 процесс",
        "price": "от 40 000 ₽",
        "features": ["Аудит процесса", "1 автоматизация", "Интеграция 2 сервисов", "Документация", "Запуск — 7 дней"]
      },
      {
        "id": "standard",
        "name": "Стандарт",
        "description": "Отдел",
        "price": "от 120 000 ₽",
        "features": ["Аудит отдела", "До 5 автоматизаций", "CRM + рассылки", "Обучение команды", "Запуск — 21 день", "Поддержка 30 дней"]
      },
      {
        "id": "premium",
        "name": "Премиум",
        "description": "Вся компания",
        "price": "от 300 000 ₽",
        "features": ["Комплексный аудит", "Неограниченные процессы", "Кастомные интеграции", "AI-автоматизации", "Запуск — 60 дней", "Поддержка 90 дней"]
      }
    ],
    "cases": [
      { "title": "Логистическая компания", "result": "Автоматизация заявок и маршрутов", "metrics": ["−60% ручной работы", "+25% скорость"] },
      { "title": "Агентство недвижимости", "result": "CRM + авто-рассылки", "metrics": ["+40% конверсия", "−50% время на лид"] }
    ],
    "faq": [
      { "question": "С какими сервисами работаете?", "answer": "Bitrix24, amoCRM, 1C, Google Workspace, Notion, Telegram, WhatsApp и 500+ других через API." },
      { "question": "Сколько времени сэкономим?", "answer": "В среднем 40-60% рабочего времени на рутинных задачах." },
      { "question": "Нужен ли программист потом?", "answer": "Нет — настраиваем так, чтобы вы могли управлять сами." }
    ]
  },
  {
    "slug": "ecosystem",
    "badge": "Full Service",
    "title": "Digital-экосистема",
    "subtitle": "Сайт + бот + CRM + AI — всё в единой системе",
    "timeline": "30–90 дней",
    "telegramLink": "https://t.me/neeklo",
    "features": [
      "Комплексная цифровизация",
      "Все продукты студии",
      "Выделенная команда",
      "Поддержка до 12 мес"
    ],
    "audiences": [
      { "icon": "Building2", "title": "Средний бизнес", "description": "Комплексная цифровизация" },
      { "icon": "Rocket", "title": "Стартапы", "description": "Быстрый запуск продукта" },
      { "icon": "Factory", "title": "Производство", "description": "Цифровая трансформация" },
      { "icon": "Store", "title": "Ритейл", "description": "Омниканальность" }
    ],
    "packages": [
      {
        "id": "basic",
        "name": "Старт",
        "description": "Базовая экосистема",
        "price": "от 200 000 ₽",
        "features": ["Сайт + Telegram-бот", "Базовая CRM", "Интеграции", "Запуск — 30 дней", "Поддержка 30 дней"]
      },
      {
        "id": "standard",
        "name": "Бизнес",
        "description": "Полная экосистема",
        "price": "от 500 000 ₽",
        "features": ["Сайт + Mini App + AI-агент", "CRM + автоматизации", "Аналитика", "Обучение", "Запуск — 60 дней", "Поддержка 90 дней"]
      },
      {
        "id": "premium",
        "name": "Корпорация",
        "description": "Под ключ",
        "price": "от 1 000 000 ₽",
        "features": ["Все продукты студии", "Индивидуальная архитектура", "Выделенная команда", "SLA", "Запуск — 90 дней", "Поддержка 12 мес"]
      }
    ],
    "cases": [
      { "title": "Сеть клиник", "result": "Единая система записи и CRM", "metrics": ["+80% онлайн-записей", "−40% нагрузка колл-центра"] },
      { "title": "Образовательный холдинг", "result": "Экосистема для 5 школ", "metrics": ["15000 учеников", "100% автоматизация"] }
    ],
    "faq": [
      { "question": "С чего начать?", "answer": "Проведём аудит и составим roadmap — определим приоритеты и этапы внедрения." },
      { "question": "Можно поэтапно?", "answer": "Да — начинаем с MVP, затем масштабируем по мере роста бизнеса." },
      { "question": "Как поддерживаете?", "answer": "Выделенный менеджер, техподдержка, регулярные апдейты и обучение команды." }
    ]
  },
  {
    "slug": "branding",
    "badge": "Design",
    "title": "Брендинг",
    "subtitle": "Логотип, фирменный стиль и гайдлайны для вашего бизнеса",
    "timeline": "7–30 дней",
    "telegramLink": "https://t.me/neeklo",
    "features": [
      "3-5 концепций",
      "Фирменные элементы",
      "Все форматы файлов",
      "Гайдлайн"
    ],
    "audiences": [
      { "icon": "Rocket", "title": "Стартапы", "description": "Бренд с нуля" },
      { "icon": "RefreshCw", "title": "Ребрендинг", "description": "Обновление имиджа" },
      { "icon": "Users", "title": "Личный бренд", "description": "Для экспертов" },
      { "icon": "Building", "title": "Компании", "description": "Корпоративный стиль" }
    ],
    "packages": [
      {
        "id": "basic",
        "name": "Логотип",
        "description": "Базовый пакет",
        "price": "от 30 000 ₽",
        "features": ["3 концепции логотипа", "Цветовая палитра", "Шрифтовая пара", "Файлы для web и печати", "Срок — 7 дней"]
      },
      {
        "id": "standard",
        "name": "Айдентика",
        "description": "Полный стиль",
        "price": "от 80 000 ₽",
        "features": ["Логотип + варианты", "Фирменные элементы", "Шаблоны документов", "Социальные сети", "Гайдлайн", "Срок — 14 дней"]
      },
      {
        "id": "premium",
        "name": "Бренд-платформа",
        "description": "Стратегия + дизайн",
        "price": "от 200 000 ₽",
        "features": ["Позиционирование", "Tone of voice", "Полная айдентика", "Брендбук", "Презентация бренда", "Срок — 30 дней"]
      }
    ],
    "cases": [
      { "title": "Fintech-стартап", "result": "Бренд с нуля за 2 недели", "metrics": ["5 концепций", "Готов к раунду"] },
      { "title": "Ресторан", "result": "Полный ребрендинг", "metrics": ["+35% узнаваемость", "Новый имидж"] }
    ],
    "faq": [
      { "question": "Сколько вариантов покажете?", "answer": "3-5 концепций на первом этапе, затем дорабатываем выбранную." },
      { "question": "Что получу в итоге?", "answer": "Все файлы (AI, SVG, PNG), гайдлайн и инструкции по использованию." },
      { "question": "Делаете naming?", "answer": "Да — генерация названий, проверка доменов и товарных знаков." }
    ]
  },
  {
    "slug": "crm",
    "badge": "CRM",
    "title": "CRM-интеграции",
    "subtitle": "Настройка и интеграция CRM под ваши бизнес-процессы",
    "timeline": "5–30 дней",
    "telegramLink": "https://t.me/neeklo",
    "features": [
      "Настройка воронок",
      "Импорт данных",
      "Интеграции",
      "Обучение команды"
    ],
    "audiences": [
      { "icon": "Users", "title": "Отделы продаж", "description": "Воронки и сделки" },
      { "icon": "Headphones", "title": "Поддержка", "description": "Тикеты и SLA" },
      { "icon": "BarChart", "title": "Маркетинг", "description": "Лиды и аналитика" },
      { "icon": "Building", "title": "Компании", "description": "Все отделы в CRM" }
    ],
    "packages": [
      {
        "id": "basic",
        "name": "Настройка",
        "description": "Базовая CRM",
        "price": "от 35 000 ₽",
        "features": ["Настройка воронок", "Импорт данных", "Обучение команды", "Срок — 5 дней", "Поддержка 14 дней"]
      },
      {
        "id": "standard",
        "name": "Интеграция",
        "description": "CRM + сервисы",
        "price": "от 80 000 ₽",
        "features": ["Полная настройка", "Интеграции (5 сервисов)", "Автоматизации", "Дашборды", "Срок — 14 дней", "Поддержка 30 дней"]
      },
      {
        "id": "premium",
        "name": "Под ключ",
        "description": "CRM-экосистема",
        "price": "от 180 000 ₽",
        "features": ["Кастомная настройка", "Неограниченные интеграции", "AI-автоматизации", "Миграция данных", "Срок — 30 дней", "Поддержка 60 дней"]
      }
    ],
    "cases": [
      { "title": "Строительная компания", "result": "Bitrix24 + интеграции", "metrics": ["+50% скорость обработки", "0 потерянных лидов"] },
      { "title": "Агентство", "result": "amoCRM + автоматизации", "metrics": ["−40% время на рутину", "+30% сделок"] }
    ],
    "faq": [
      { "question": "Какие CRM поддерживаете?", "answer": "Bitrix24, amoCRM, HubSpot, Salesforce, Pipedrive и другие." },
      { "question": "Можно перенести данные?", "answer": "Да — мигрируем из любой системы с сохранением истории." },
      { "question": "Обучите команду?", "answer": "Да — проводим обучение и даём видео-инструкции." }
    ]
  },
  {
    "slug": "mobile-app",
    "badge": "Mobile",
    "title": "Мобильное приложение",
    "subtitle": "iOS и Android приложения для вашего бизнеса",
    "timeline": "6–16 недель",
    "telegramLink": "https://t.me/neeklo",
    "features": [
      "iOS + Android",
      "Push-уведомления",
      "Публикация в сторах",
      "Аналитика"
    ],
    "audiences": [
      { "icon": "Rocket", "title": "Стартапы", "description": "MVP за 2 месяца" },
      { "icon": "ShoppingBag", "title": "E-commerce", "description": "Магазин в кармане" },
      { "icon": "Building", "title": "Бизнес", "description": "Внутренние сервисы" },
      { "icon": "Heart", "title": "Lifestyle", "description": "Сервисные приложения" }
    ],
    "packages": [
      {
        "id": "basic",
        "name": "MVP",
        "description": "Минимальный продукт",
        "price": "от 300 000 ₽",
        "features": ["iOS или Android", "До 10 экранов", "Базовый backend", "Публикация в сторе", "Срок — 6 недель"]
      },
      {
        "id": "standard",
        "name": "Стандарт",
        "description": "Полноценное приложение",
        "price": "от 600 000 ₽",
        "features": ["iOS + Android", "До 25 экранов", "Push-уведомления", "Аналитика", "Срок — 10 недель", "Поддержка 30 дней"]
      },
      {
        "id": "premium",
        "name": "Премиум",
        "description": "Сложный продукт",
        "price": "от 1 200 000 ₽",
        "features": ["Кастомный дизайн", "Неограниченный функционал", "Интеграции", "AI-функции", "Срок — 16 недель", "Поддержка 90 дней"]
      }
    ],
    "cases": [
      { "title": "Фитнес-сервис", "result": "Приложение для тренировок", "metrics": ["50K скачиваний", "4.8 рейтинг"] },
      { "title": "Доставка", "result": "Приложение для курьеров", "metrics": ["+60% эффективность", "500 курьеров"] }
    ],
    "faq": [
      { "question": "На чём разрабатываете?", "answer": "React Native для кроссплатформы, Swift/Kotlin для нативных решений." },
      { "question": "Поможете с публикацией?", "answer": "Да — полное сопровождение в App Store и Google Play." },
      { "question": "Нужен ли свой сервер?", "answer": "Можем развернуть backend на нашем облаке или ваших серверах." }
    ]
  },
  {
    "slug": "support",
    "badge": "Support",
    "title": "Техподдержка",
    "subtitle": "Поддержка и развитие ваших сайтов, ботов и приложений",
    "timeline": "Подписка",
    "telegramLink": "https://t.me/neeklo",
    "features": [
      "Мелкие правки",
      "Доработки функционала",
      "Мониторинг",
      "Быстрая реакция"
    ],
    "audiences": [
      { "icon": "Globe", "title": "Сайты", "description": "Обновления и правки" },
      { "icon": "Bot", "title": "Боты", "description": "Доработки и мониторинг" },
      { "icon": "Smartphone", "title": "Приложения", "description": "Обновления и баги" },
      { "icon": "Server", "title": "Инфраструктура", "description": "Серверы и DevOps" }
    ],
    "packages": [
      {
        "id": "basic",
        "name": "Базовый",
        "description": "10 часов/месяц",
        "price": "от 25 000 ₽/мес",
        "features": ["10 часов работы", "Мелкие правки", "Ответ за 24 часа", "Email-поддержка", "Отчёт раз в месяц"]
      },
      {
        "id": "standard",
        "name": "Стандарт",
        "description": "25 часов/месяц",
        "price": "от 50 000 ₽/мес",
        "features": ["25 часов работы", "Доработки функционала", "Ответ за 4 часа", "Telegram-канал", "Еженедельный отчёт"]
      },
      {
        "id": "premium",
        "name": "Премиум",
        "description": "Безлимит",
        "price": "от 120 000 ₽/мес",
        "features": ["Неограниченные часы", "Приоритетные задачи", "Ответ за 1 час", "Выделенный менеджер", "Проактивный мониторинг"]
      }
    ],
    "cases": [
      { "title": "E-commerce", "result": "Поддержка магазина 24/7", "metrics": ["99.9% uptime", "15 мин реакция"] },
      { "title": "SaaS-платформа", "result": "Развитие продукта", "metrics": ["+20 фич/месяц", "0 критичных багов"] }
    ],
    "faq": [
      { "question": "Как быстро отвечаете?", "answer": "Зависит от тарифа: от 24 часов до 1 часа на критичные задачи." },
      { "question": "Что входит в поддержку?", "answer": "Правки, обновления, мониторинг, резервное копирование, консультации." },
      { "question": "Можно увеличить часы?", "answer": "Да — дополнительные часы оплачиваются отдельно по фиксированной ставке." }
    ]
  },
  {
    "slug": "consulting",
    "badge": "Consulting",
    "title": "Консалтинг",
    "subtitle": "Digital-стратегия и выбор правильных решений для бизнеса",
    "timeline": "1–4 недели",
    "telegramLink": "https://t.me/neeklo",
    "features": [
      "Аудит процессов",
      "Roadmap продукта",
      "Выбор технологий",
      "Оценка бюджета"
    ],
    "audiences": [
      { "icon": "Lightbulb", "title": "Стартапы", "description": "Product-market fit" },
      { "icon": "Building", "title": "Бизнес", "description": "Digital-трансформация" },
      { "icon": "TrendingUp", "title": "Рост", "description": "Масштабирование" },
      { "icon": "Shield", "title": "Оптимизация", "description": "Аудит и улучшения" }
    ],
    "packages": [
      {
        "id": "basic",
        "name": "Консультация",
        "description": "Разовая сессия",
        "price": "от 15 000 ₽",
        "features": ["1.5 часа консультации", "Ответы на вопросы", "Рекомендации", "Запись сессии", "Чек-лист действий"]
      },
      {
        "id": "standard",
        "name": "Аудит",
        "description": "Глубокий анализ",
        "price": "от 60 000 ₽",
        "features": ["Аудит digital-активов", "Анализ конкурентов", "Roadmap развития", "Приоритеты задач", "Презентация"]
      },
      {
        "id": "premium",
        "name": "Стратегия",
        "description": "Полное сопровождение",
        "price": "от 150 000 ₽",
        "features": ["3 месяца работы", "Еженедельные созвоны", "Контроль реализации", "Корректировка плана", "Доступ к экспертам"]
      }
    ],
    "cases": [
      { "title": "Производство", "result": "Digital-стратегия на год", "metrics": ["Roadmap 12 мес", "+40% онлайн-продаж"] },
      { "title": "Ритейл", "result": "Аудит и оптимизация", "metrics": ["−30% затраты на IT", "+50% скорость"] }
    ],
    "faq": [
      { "question": "Чем поможете?", "answer": "Поможем выбрать технологии, приоритизировать задачи, избежать типичных ошибок." },
      { "question": "Это только разговоры?", "answer": "Нет — даём конкретные рекомендации, чек-листы и roadmap с дедлайнами." },
      { "question": "Можете потом реализовать?", "answer": "Да — после консалтинга можем взять проект в разработку." }
    ]
  }
]